README.md
setup.py
app/__init__.py
core/Page.py
core/Request.py
core/Site.py
core/Spider.py
core/__init__.py
core/common.py
core/downloader/Downloader.py
core/downloader/DriverDownloader.py
core/downloader/HttpDownloader.py
core/downloader/__init__.py
core/pipeline/Pipeline.py
core/pipeline/__init__.py
core/processor/PageProcessor.py
core/processor/__init__.py
core/scheduler/DuplicateRemovedScheduler.py
core/scheduler/QueueScheduler.py
core/scheduler/Scheduler.py
core/scheduler/__init__.py
core/utils/__init__.py
humanSpider.egg-info/PKG-INFO
humanSpider.egg-info/SOURCES.txt
humanSpider.egg-info/dependency_links.txt
humanSpider.egg-info/not-zip-safe
humanSpider.egg-info/requires.txt
humanSpider.egg-info/top_level.txt